jmdevice/__init__.py
jmdevice/__pycache__/__init__.cpython-39.pyc
jmdevice/kit/__init__.py
jmdevice/kit/adbkit.py
jmdevice/kit/ios_mapping.json
jmdevice/kit/ioskit.py
jmdevice/static/adb/linux/adb
jmdevice/static/adb/linux_arm/adb
jmdevice/static/adb/mac/adb
jmdevice/static/adb/windows/AdbWinApi.dll
jmdevice/static/adb/windows/AdbWinUsbApi.dll
jmdevice/static/adb/windows/adb.exe
jmdevice/tools/__init__.py
jmdevice/tools/cmdkit.py
jmdevice-0.0.2.dist-info/LICENSE
jmdevice-0.0.2.dist-info/METADATA
jmdevice-0.0.2.dist-info/WHEEL
jmdevice-0.0.2.dist-info/top_level.txt
jmdevice-0.0.2.dist-info/zip-safe
jmdevice-0.0.2.dist-info/RECORD
