Metadata-Version: 2.1
Name: jmdevice
Version: 0.0.2
Summary: jmdevice
Home-page: https://github.com/logan62334/jmdevice.git
Author: mafei
License: MIT Licence
Platform: any
Requires-Python: >=3
License-File: LICENSE
Requires-Dist: tidevice
